seria/constants.py
seria/logging.py
seria/utils.py
seria/dpy/ui.py
seria/tortoise/model.py
seria_library-1.5.5.dist-info/METADATA
seria_library-1.5.5.dist-info/WHEEL
seria_library-1.5.5.dist-info/licenses/LICENSE
seria_library-1.5.5.dist-info/RECORD
