Metadata-Version: 2.4
Name: seria-library
Version: 1.5.5
Summary: Seria's library (of code)
Author-email: seria <seria.ati@gmail.com>
License: GNU GENERAL PUBLIC LICENSE
License-File: LICENSE
Requires-Python: >=3.11
Provides-Extra: all
Requires-Dist: aiofiles>=24.1.0; extra == 'all'
Requires-Dist: discord-py>=2.5.0; extra == 'all'
Requires-Dist: orjson>=3.10.15; extra == 'all'
Requires-Dist: pyyaml>=6.0.2; extra == 'all'
Requires-Dist: tortoise-orm>=0.24.1; extra == 'all'
Provides-Extra: dpy
Requires-Dist: discord-py>=2.5.0; extra == 'dpy'
Provides-Extra: files
Requires-Dist: aiofiles>=24.1.0; extra == 'files'
Requires-Dist: aiohttp>=3.11.13; extra == 'files'
Requires-Dist: orjson>=3.10.15; extra == 'files'
Requires-Dist: pyyaml>=6.0.2; extra == 'files'
Provides-Extra: tortoise
Requires-Dist: tortoise-orm>=0.24.1; extra == 'tortoise'
